{
    "Advanced object oriented programming": {
        "Time": "Jun 07 2016 12:00", 
        "Year": 2
    }, 
    "Algorithms pt.1": {
        "Time": "Jun 14 2016 09:00", 
        "Year": 2
    }, 
    "Algorithms pt.2": {
        "Time": "Jun 26 2016 11:00", 
        "Year": 4
    }, 
    "Automates and formal languages": {
        "Time": "Jun 10 2016 11:00", 
        "Year": 2
    }, 
    "Calculus 1": {
        "Time": "Jun 30 2016 14:00", 
        "Year": 1
    }, 
    "Compilation": {
        "Time": "Jun 08 2016 17:00", 
        "Year": 3
    }, 
    "Computer Architecture pt.1": {
        "Time": "Jun 07 2016 12:00", 
        "Year": 1
    }, 
    "Computer Architecture pt.2": {
        "Time": "Jun 09 2016 10:00", 
        "Year": 1
    }, 
    "Data structures": {
        "Time": "Jun 19 2016 14:00", 
        "Year": 2
    }, 
    "Introduction to computer networking": {
        "Time": "Jun 14 2016 13:00", 
        "Year": 3
    }, 
    "Introduction to statistics and probablilty": {
        "Time": "Jun 16 2016 15:00", 
        "Year": 2
    }, 
    "Numerical analysis": {
        "Time": "Jun 22 2016 10:00", 
        "Year": 3
    }, 
    "Operating Systems": {
        "Time": "Jun 27 2016 17:00", 
        "Year": 3
    }, 
    "Physics for software engeneres": {
        "Time": "Jun 15 2016 11:00", 
        "Year": 1
    }, 
    "Reliability": {
        "Time": "Jun 10 2016 09:00", 
        "Year": 4
    }, 
    "Software Security": {
        "Time": "Jun 16 2016 13:00", 
        "Year": 4
    }
}